foster2020/__init__.py
foster2020/decision_surface.py
foster2020/features_pipeline.py
foster2020/features_pipeline_3.py
foster2020/sample_data.py
foster2020/spam_data.py
foster2020-0.1.data/scripts/foster2020
foster2020-0.1.dist-info/METADATA
foster2020-0.1.dist-info/WHEEL
foster2020-0.1.dist-info/top_level.txt
foster2020-0.1.dist-info/RECORD
